spanner_analytics/__init__.py
spanner_analytics/conftest.py
spanner_analytics/database.py
spanner_analytics/database_test.py
spanner_analytics/magic.py
spanner_analytics/magic_test.py
spanner_analytics-1.0.1.dist-info/LICENSE
spanner_analytics-1.0.1.dist-info/METADATA
spanner_analytics-1.0.1.dist-info/WHEEL
spanner_analytics-1.0.1.dist-info/top_level.txt
spanner_analytics-1.0.1.dist-info/RECORD
