Metadata-Version: 2.1
Name: spanner-analytics
Version: 1.0.1
Project-URL: Homepage, https://github.com/cloudspannerecosystem/spanner-analytics
License-File: LICENSE
Requires-Dist: google-cloud-spanner
Requires-Dist: google-auth
Requires-Dist: numpy
Requires-Dist: pandas
Provides-Extra: magic
Requires-Dist: jupyter-client ; extra == 'magic'
Requires-Dist: ipython ; extra == 'magic'
Provides-Extra: test
Requires-Dist: pytest ; extra == 'test'
Requires-Dist: nbformat ; extra == 'test'
Requires-Dist: nbconvert ; extra == 'test'
Requires-Dist: jupyter ; extra == 'test'
